pychelin/parser.py
pychelin/reverse_geocoder.py
pychelin/__init__.py
pychelin/geocoder.py
pychelin-0.1.dist-info/DESCRIPTION.rst
pychelin-0.1.dist-info/top_level.txt
pychelin-0.1.dist-info/pydist.json
pychelin-0.1.dist-info/zip-safe
pychelin-0.1.dist-info/METADATA
pychelin-0.1.dist-info/RECORD
pychelin-0.1.dist-info/WHEEL
