Metadata-Version: 2.0
Name: pychelin
Version: 0.1
Summary: Module that dialog with viamichelin api.
Home-page: https://bitbucket.org/xcg/pychelin
Author: Anael Lorimier
Author-email: anael.lorimier@xcg-consulting.fr
License: MIT
Keywords: pychelin
Platform: UNKNOWN
Requires-Dist: requests
Requires-Dist: iso3166
